dnngior/MSEED_compounds.py
dnngior/MSEED_reactions.py
dnngior/NN_Predictor.py
dnngior/NN_Trainer.py
dnngior/__init__.py
dnngior/addBGExchanges.py
dnngior/addExchanges.py
dnngior/build_model.py
dnngior/fasta2model_CLI.py
dnngior/files/NN/NN_BG.npz
dnngior/files/NN/NN_MS.npz
dnngior/files/NN/__init__.py
dnngior/files/NN/rxn_ids_BiGG.npy
dnngior/files/NN/rxn_ids_ModelSEED.npy
dnngior/files/__init__.py
dnngior/files/biochemistry/Aliases/Cpd_Source.txt
dnngior/files/biochemistry/Aliases/README.md
dnngior/files/biochemistry/Aliases/Rxn_Source.txt
dnngior/files/biochemistry/Aliases/Source_Classifiers.txt
dnngior/files/biochemistry/Aliases/Unique_ModelSEED_Compound_Aliases.txt
dnngior/files/biochemistry/Aliases/Unique_ModelSEED_Compound_Names.txt
dnngior/files/biochemistry/Aliases/Unique_ModelSEED_Reaction_Aliases.txt
dnngior/files/biochemistry/Aliases/Unique_ModelSEED_Reaction_ECs.txt
dnngior/files/biochemistry/Aliases/Unique_ModelSEED_Reaction_Names.txt
dnngior/files/biochemistry/Aliases/Unique_ModelSEED_Reaction_Pathways.txt
dnngior/files/biochemistry/Aliases/__init__.py
dnngior/files/biochemistry/README.md
dnngior/files/biochemistry/__init__.py
dnngior/files/biochemistry/bigg_compounds.tsv
dnngior/files/biochemistry/compounds.tsv.tar.gz
dnngior/files/biochemistry/reactions.tsv.tar.gz
dnngior/files/models/BiGG_exchanges.sbml
dnngior/files/models/MS_exchanges.sbml
dnngior/files/models/__init__.py
dnngior/gapfill_class.py
dnngior/gapfill_function.py
dnngior/reaction_class.py
dnngior/variables.py
dnngior-0.0.5.dist-info/LICENSE
dnngior-0.0.5.dist-info/METADATA
dnngior-0.0.5.dist-info/WHEEL
dnngior-0.0.5.dist-info/RECORD
