Metadata-Version: 2.1
Name: dnngior
Version: 0.0.5
Summary: build high-quality genome-scale metabolic model by using a deep neural network to guide gapfilling
Author: Haris Zafeiropoulos
Author-email: haris.zafeiropoulos@kuleuven.be
Requires-Python: >=3.9,<3.12
Classifier: Programming Language :: Python :: 3
Classifier: Programming Language :: Python :: 3.9
Classifier: Programming Language :: Python :: 3.10
Classifier: Programming Language :: Python :: 3.11
Requires-Dist: cobra (<=0.23.0)
Requires-Dist: gurobipy (>=10.0.1,<11.0.0)
